Workbook

Sheet Executive Summary
A1: Metric | B1: 2026 | C1: 2027 | D1: 2028 | E1: 2029 | F1: 2030
A2: Customers | B2: 28 | C2: 86 | D2: 205 | E2: 430 | F2: 760
A3: Active seats | B3: 126 | C3: 430 | D3: 1230 | E3: 3010 | F3: 6080
A4: ARR | B4: 125000 | C4: 520000 | D4: 1590000 | E4: 4080000 | F4: 8320000
A5: Gross margin | B5: 0.63 | C5: 0.68 | D5: 0.73 | E5: 0.77 | F5: 0.79
A6: Ending cash | B6: 1120000 | C6: 410000 | D6: -260000 | E6: 1040000 | F6: 3020000

Sheet Assumptions
A1: Assumption | B1: Value | C1: Unit | D1: Notes
A2: Solo price | B2: 69 | C2: $ / count / % | D2: Canonical prompt-aligned assumption
A3: Team price | B3: 249 | C3: $ / count / % | D3: Canonical prompt-aligned assumption
A4: Business price | B4: 599 | C4: $ / count / % | D4: Canonical prompt-aligned assumption
A5: Starting customers | B5: 9 | C5: $ / count / % | D5: Canonical prompt-aligned assumption
A6: Starting seats | B6: 42 | C6: $ / count / % | D6: Canonical prompt-aligned assumption
A7: Starting MRR | B7: 3200 | C7: $ / count / % | D7: Canonical prompt-aligned assumption
A8: Seed raise | B8: 1500000 | C8: $ / count / % | D8: Canonical prompt-aligned assumption
A9: Gross margin target | B9: 0.76 | C9: $ / count / % | D9: Canonical prompt-aligned assumption
A10: Monthly logo churn | B10: 0.025 | C10: $ / count / % | D10: Canonical prompt-aligned assumption
A11: AI cost per active seat | B11: 8 | C11: $ / count / % | D11: Canonical prompt-aligned assumption
A12: Storage cost per active seat | B12: 2 | C12: $ / count / % | D12: Canonical prompt-aligned assumption

Sheet Customer Growth
A1: Line item | B1: 2026 | C1: 2027 | D1: 2028 | E1: 2029 | F1: 2030
A2: Beginning customers | B2: 9 | C2: 28 | D2: 86 | E2: 205 | F2: 430
A3: New customers | B3: 21 | C3: 66 | D3: 142 | E3: 276 | F3: 432
A4: Logo churn | B4: -2 | C4: -8 | D4: -23 | E4: -51 | F4: -102
A5: Ending customers | B5: =B2+B3+B4 | C5: =C2+C3+C4 | D5: =D2+D3+D4 | E5: =E2+E3+E4 | F5: =F2+F3+F4

Sheet Revenue Model
A1: Line item | B1: 2026 | C1: 2027 | D1: 2028 | E1: 2029 | F1: 2030
A2: Subscription revenue | B2: 88000 | C2: 390000 | D2: 1210000 | E2: 3150000 | F2: 6500000
A3: Usage expansion | B3: 9000 | C3: 54000 | D3: 210000 | E3: 620000 | F3: 1320000
A4: Setup / onboarding | B4: 28000 | C4: 76000 | D4: 170000 | E4: 310000 | F4: 500000
A5: Total revenue | B5: =SUM(B2:B4) | C5: =SUM(C2:C4) | D5: =SUM(D2:D4) | E5: =SUM(E2:E4) | F5: =SUM(F2:F4)

Sheet COGS Service Costs
A1: Line item | B1: 2026 | C1: 2027 | D1: 2028 | E1: 2029 | F1: 2030
A2: AI inference | B2: 21000 | C2: 81000 | D2: 238000 | E2: 570000 | F2: 1130000
A3: Storage and hosting | B3: 15000 | C3: 52000 | D3: 150000 | E3: 350000 | F3: 710000
A4: Support and onboarding | B4: 10000 | C4: 35000 | D4: 98000 | E4: 210000 | F4: 420000
A5: Total COGS | B5: =SUM(B2:B4) | C5: =SUM(C2:C4) | D5: =SUM(D2:D4) | E5: =SUM(E2:E4) | F5: =SUM(F2:F4)

Sheet Headcount Plan
A1: Line item | B1: 2026 | C1: 2027 | D1: 2028 | E1: 2029 | F1: 2030
A2: Founder | B2: 1 | C2: 1 | D2: 1 | E2: 1 | F2: 1
A3: Engineering | B3: 1 | C3: 3 | D3: 6 | E3: 10 | F3: 16
A4: Product/design | B4: 1 | C4: 2 | D4: 3 | E4: 5 | F4: 8
A5: GTM/support | B5: 1 | C5: 2 | D5: 5 | E5: 10 | F5: 18
A6: Total FTE | B6: =SUM(B2:B5) | C6: =SUM(C2:C5) | D6: =SUM(D2:D5) | E6: =SUM(E2:E5) | F6: =SUM(F2:F5)

Sheet OpEx
A1: Line item | B1: 2026 | C1: 2027 | D1: 2028 | E1: 2029 | F1: 2030
A2: Payroll | B2: 420000 | C2: 980000 | D2: 1850000 | E2: 3350000 | F2: 5550000
A3: Marketing | B3: 90000 | C3: 260000 | D3: 620000 | E3: 1200000 | F3: 2200000
A4: G&A / tools | B4: 85000 | C4: 150000 | D4: 260000 | E4: 430000 | F4: 710000
A5: Total OpEx | B5: =SUM(B2:B4) | C5: =SUM(C2:C4) | D5: =SUM(D2:D4) | E5: =SUM(E2:E4) | F5: =SUM(F2:F4)

Sheet P&L
A1: Line item | B1: 2026 | C1: 2027 | D1: 2028 | E1: 2029 | F1: 2030
A2: Revenue | B2: ='Revenue Model'!B5 | C2: ='Revenue Model'!C5 | D2: ='Revenue Model'!D5 | E2: ='Revenue Model'!E5 | F2: ='Revenue Model'!F5
A3: COGS | B3: ='COGS Service Costs'!B5 | C3: ='COGS Service Costs'!C5 | D3: ='COGS Service Costs'!D5 | E3: ='COGS Service Costs'!E5 | F3: ='COGS Service Costs'!F5
A4: Gross profit | B4: =B2-B3 | C4: =C2-C3 | D4: =D2-D3 | E4: =E2-E3 | F4: =F2-F3
A5: OpEx | B5: ='OpEx'!B5 | C5: ='OpEx'!C5 | D5: ='OpEx'!D5 | E5: ='OpEx'!E5 | F5: ='OpEx'!F5
A6: Net income | B6: =B4-B5 | C6: =C4-C5 | D6: =D4-D5 | E6: =E4-E5 | F6: =F4-F5

Sheet Cash Runway
A1: Line item | B1: 2026 | C1: 2027 | D1: 2028 | E1: 2029 | F1: 2030
A2: Opening cash | B2: 1500000 | C2: =B5 | D2: =C5 | E2: =D5+1500000 | F2: =E5
A3: Net income | B3: ='P&L'!B6 | C3: ='P&L'!C6 | D3: ='P&L'!D6 | E3: ='P&L'!E6 | F3: ='P&L'!F6
A4: Financing | B4: 0 | C4: 0 | D4: 0 | E4: 1500000 | F4: 0
A5: Ending cash | B5: =B2+B3+B4 | C5: =C2+C3+C4 | D5: =D2+D3+D4 | E5: =E2+E3+E4 | F5: =F2+F3+F4

Sheet Pricing & Packaging
A1: Plan | B1: Monthly price | C1: Primary buyer | D1: Included
A2: Solo | B2: 69 | C2: Independent consultant | D2: Capture, 10 projects, report drafts
A3: Team | B3: 249 | C3: Small service team | D3: Shared workspace, templates, portal
A4: Business | B4: 599 | C4: Higher-volume operator | D4: Priority onboarding, usage expansion, admin controls

Sheet Scenarios
A1: Scenario | B1: 2028 ARR | C1: Gross margin | D1: Runway note
A2: Conservative | B2: 980000 | C2: 0.68 | D2: Need bridge before 2029
A3: Base | B3: 1590000 | C3: 0.73 | D3: Raise after traction inflection
A4: Aggressive | B4: 2450000 | C4: 0.77 | D4: Can support larger seed extension

Sheet Charts
A1: Year | B1: 2026 | C1: 2027 | D1: 2028 | E1: 2029 | F1: 2030
A2: ARR | B2: 125000 | C2: 520000 | D2: 1590000 | E2: 4080000 | F2: 8320000
A3: Customers | B3: 28 | C3: 86 | D3: 205 | E3: 430 | F3: 760
